mi_script.py
mi_proyecto_pdm-0.1.0.dist-info/METADATA
mi_proyecto_pdm-0.1.0.dist-info/WHEEL
mi_proyecto_pdm-0.1.0.dist-info/top_level.txt
mi_proyecto_pdm-0.1.0.dist-info/RECORD
