Metadata-Version: 2.4
Name: mi_proyecto_pdm
Version: 0.1.0
Summary: Default template for PDM package
Author-email: Andres Gonzalez <andres_fgonzalez28@soy.sena.edu.co>
License: MIT
Requires-Python: ==3.13.*
Requires-Dist: Django>=5.2.4
Requires-Dist: requests>=2.32.4
Requires-Dist: psycopg2-binary~=2.9
Provides-Extra: docs
Requires-Dist: mkdocs-material>=9.6.15; extra == "docs"
